pyshaiii/__init__.py
pyshaiii/main.py
pyshaiii-0.1.1.dist-info/WHEEL
pyshaiii-0.1.1.dist-info/entry_points.txt
pyshaiii-0.1.1.dist-info/METADATA
pyshaiii-0.1.1.dist-info/RECORD
