Metadata-Version: 2.3
Name: pyshaiii
Version: 0.1.1
Summary: Python implementation of the SHA-3 hash algorithm :)
Keywords: python,sha3,keccak
Author: SimoneFelici
Author-email: SimoneFelici <felicisimone9@gmail.com>
Requires-Python: >=3.12
Project-URL: Documentation, https://github.com/SimoneFelici/PyshaIII?tab=readme-ov-file#pyshaiii
Project-URL: Issues, https://github.com/SimoneFelici/PyshaIII/issues
Project-URL: Repository, https://github.com/SimoneFelici/PyshaIII
